metrics_python/__init__.py
metrics_python/asgi/__init__.py
metrics_python/asgi/_metrics.py
metrics_python/asgi/_middleware.py
metrics_python/asgi/tests/__init__.py
metrics_python/asgi/tests/test_fastapi_middleware.py
metrics_python/asgi/tests/test_starlette_middleware.py
metrics_python/celery/__init__.py
metrics_python/celery/_constants.py
metrics_python/celery/_metrics.py
metrics_python/celery/_setup.py
metrics_python/celery/_signals.py
metrics_python/celery/tests/__init__.py
metrics_python/celery/tests/test_setup.py
metrics_python/conftest.py
metrics_python/constants.py
metrics_python/django/__init__.py
metrics_python/django/_metrics.py
metrics_python/django/_query_counter.py
metrics_python/django/_utils.py
metrics_python/django/cache.py
metrics_python/django/celery.py
metrics_python/django/conf.py
metrics_python/django/middleware.py
metrics_python/django/postgres_engine/__init__.py
metrics_python/django/postgres_engine/base.py
metrics_python/django/signals.py
metrics_python/django/tests/__init__.py
metrics_python/django/tests/app/__init__.py
metrics_python/django/tests/app/django_ninja.py
metrics_python/django/tests/app/management/__init__.py
metrics_python/django/tests/app/management/commands/__init__.py
metrics_python/django/tests/app/management/commands/test.py
metrics_python/django/tests/app/view.py
metrics_python/django/tests/settings.py
metrics_python/django/tests/test_cache.py
metrics_python/django/tests/test_django_ninja/test_middleware.py
metrics_python/django/tests/test_middleware/__init__.py
metrics_python/django/tests/test_middleware/test_metrics_middleware.py
metrics_python/django/tests/test_signals.py
metrics_python/django/tests/urls.py
metrics_python/django_api_decorator/__init__.py
metrics_python/django_api_decorator/_metrics.py
metrics_python/django_api_decorator/_middleware.py
metrics_python/django_ninja/__init__.py
metrics_python/django_ninja/_metrics.py
metrics_python/django_ninja/_middleware.py
metrics_python/django_ninja/_utils.py
metrics_python-0.3.1.dist-info/METADATA
metrics_python-0.3.1.dist-info/WHEEL
metrics_python-0.3.1.dist-info/RECORD
