Metadata-Version: 2.1
Name: metrics-python
Version: 0.3.1
Summary: Generic set of metrics for Python applications.
Author: Eirik Martiniussen Sylliaas
Author-email: eirik@sylliaas.no
Requires-Python: >=3.11,<3.14
Classifier: Programming Language :: Python :: 3
Classifier: Programming Language :: Python :: 3.11
Classifier: Programming Language :: Python :: 3.12
